scanapi/__init__.py
scanapi/__main__.py
scanapi/cli.py
scanapi/config_loader.py
scanapi/console.py
scanapi/errors.py
scanapi/evaluators/__init__.py
scanapi/evaluators/code_evaluator.py
scanapi/evaluators/spec_evaluator.py
scanapi/evaluators/string_evaluator.py
scanapi/exit_code.py
scanapi/hide_utils.py
scanapi/py.typed
scanapi/reporter.py
scanapi/scan.py
scanapi/session.py
scanapi/settings.py
scanapi/template_render.py
scanapi/templates/report.html
scanapi/test_status.py
scanapi/tree/__init__.py
scanapi/tree/endpoint_node.py
scanapi/tree/request_node.py
scanapi/tree/testing_node.py
scanapi/tree/tree_keys.py
scanapi/utils.py
scanapi-2.12.0.dist-info/LICENSE
scanapi-2.12.0.dist-info/METADATA
scanapi-2.12.0.dist-info/WHEEL
scanapi-2.12.0.dist-info/entry_points.txt
scanapi-2.12.0.dist-info/RECORD
