Metadata-Version: 2.3
Name: scanapi
Version: 2.12.0
Summary: Automated Testing and Documentation for your REST API
License: MIT
Keywords: python,scanapi,tests,end2end,endtoend,integration tests,json,apis,api rest
Author: The ScanAPI Organization
Author-email: cmaiacd@gmail.com
Requires-Python: >=3.10,<4.0
Classifier: License :: OSI Approved :: MIT License
Classifier: Programming Language :: Python :: 3
Classifier: Programming Language :: Python :: 3.10
Classifier: Programming Language :: Python :: 3.11
Classifier: Programming Language :: Python :: 3.12
Classifier: Programming Language :: Python :: 3.13
Requires-Dist: Jinja2 (>=3.1.0,<3.2.0)
Requires-Dist: MarkupSafe (==2.1.2)
Requires-Dist: PyYAML (>=6.0.2,<6.1.0)
Requires-Dist: appdirs (>=1.4.4,<2.0.0)
Requires-Dist: click (>=8.1.3)
Requires-Dist: curlify2 (>=1.0.1,<2.0.0)
Requires-Dist: httpx (>=0.27.0,<0.28.0)
Requires-Dist: packaging (>=24.0,<25.0)
Requires-Dist: rich (==14.0.0)
Project-URL: Homepage, https://scanapi.dev/
Project-URL: Repository, https://github.com/scanapi/scanapi
